usbtingobus.py
python_can_usbtingo-1.0.2.dist-info/LICENSE.txt
python_can_usbtingo-1.0.2.dist-info/METADATA
python_can_usbtingo-1.0.2.dist-info/WHEEL
python_can_usbtingo-1.0.2.dist-info/entry_points.txt
python_can_usbtingo-1.0.2.dist-info/top_level.txt
python_can_usbtingo-1.0.2.dist-info/RECORD
