Metadata-Version: 2.1
Name: python-can-usbtingo
Version: 1.0.2
Summary: Python-can USBtingo
Home-page: https://github.com/EmbedME/python-can-usbtingo
Author: Thomas Fischl
Author-email: tfischl@gmx.de
License: UNKNOWN
Platform: UNKNOWN
Classifier: Programming Language :: Python :: 3
Classifier: License :: OSI Approved :: GNU Lesser General Public License v3 (LGPLv3)
Classifier: Operating System :: OS Independent
Requires-Python: >=3.8
License-File: LICENSE.txt
Requires-Dist: libusb1
Requires-Dist: python-can
